{"note":"This file is an internal implementation detail to speed up HTML report generation. Its format can change at any time. You might be looking for the JSON report: https://coverage.rtfd.io/cmd.html#cmd-json","format":5,"version":"7.5.3","globals":"b53dfcce7863f2b6e6c1d0e7d68d96cc","files":{"z_45fa4dfa6d22ebde___init___py":{"hash":"82fd21b41c48ccc94481a9b3418f3e65","index":{"url":"z_45fa4dfa6d22ebde___init___py.html","file":"workflow/config/__init__.py","description":"","nums":{"precision":0,"n_files":1,"n_statements":8,"n_excluded":0,"n_missing":0,"n_branches":0,"n_partial_branches":0,"n_missing_branches":0}}},"z_75f72d28b36d40ec_analyze_bitcoin_prices_py":{"hash":"0e1a83b2564fce0af5bbe59aff60f9d0","index":{"url":"z_75f72d28b36d40ec_analyze_bitcoin_prices_py.html","file":"workflow/flows/analyze_bitcoin_prices.py","description":"","nums":{"precision":0,"n_files":1,"n_statements":15,"n_excluded":0,"n_missing":1,"n_branches":0,"n_partial_branches":0,"n_missing_branches":0}}},"z_75f72d28b36d40ec_trending_coins_py":{"hash":"8dc1ac969197b796fad36044fc908bac","index":{"url":"z_75f72d28b36d40ec_trending_coins_py.html","file":"workflow/flows/trending_coins.py","description":"","nums":{"precision":0,"n_files":1,"n_statements":14,"n_excluded":0,"n_missing":1,"n_branches":0,"n_partial_branches":0,"n_missing_branches":0}}},"z_197790968570823d_coins_py":{"hash":"19de248597b293ea3367f12b60aadd62","index":{"url":"z_197790968570823d_coins_py.html","file":"workflow/schemas/coins.py","description":"","nums":{"precision":0,"n_files":1,"n_statements":13,"n_excluded":0,"n_missing":0,"n_branches":0,"n_partial_branches":0,"n_missing_branches":0}}},"z_197790968570823d_coins_market_chart_api_response_py":{"hash":"b22b432261ea5ec77daa4603d39b95ce","index":{"url":"z_197790968570823d_coins_market_chart_api_response_py.html","file":"workflow/schemas/coins_market_chart_api_response.py","description":"","nums":{"precision":0,"n_files":1,"n_statements":6,"n_excluded":0,"n_missing":0,"n_branches":0,"n_partial_branches":0,"n_missing_branches":0}}},"z_197790968570823d_coins_trending_api_response_py":{"hash":"afbe6ed41278212008853fbc49bb3f40","index":{"url":"z_197790968570823d_coins_trending_api_response_py.html","file":"workflow/schemas/coins_trending_api_response.py","description":"","nums":{"precision":0,"n_files":1,"n_statements":22,"n_excluded":0,"n_missing":0,"n_branches":0,"n_partial_branches":0,"n_missing_branches":0}}},"z_197790968570823d_market_chart_py":{"hash":"0bcf96458dba23f1269dbe54970c61a6","index":{"url":"z_197790968570823d_market_chart_py.html","file":"workflow/schemas/market_chart.py","description":"","nums":{"precision":0,"n_files":1,"n_statements":14,"n_excluded":0,"n_missing":0,"n_branches":0,"n_partial_branches":0,"n_missing_branches":0}}},"z_d85b5e27f0686b9e_extract_py":{"hash":"a2f8b170460fa4c68c7f76ba66dee612","index":{"url":"z_d85b5e27f0686b9e_extract_py.html","file":"workflow/tasks/extract.py","description":"","nums":{"precision":0,"n_files":1,"n_statements":26,"n_excluded":0,"n_missing":0,"n_branches":0,"n_partial_branches":0,"n_missing_branches":0}}},"z_d85b5e27f0686b9e_notify_py":{"hash":"6c0963f4c61434b8403d57b81bebccbe","index":{"url":"z_d85b5e27f0686b9e_notify_py.html","file":"workflow/tasks/notify.py","description":"","nums":{"precision":0,"n_files":1,"n_statements":19,"n_excluded":0,"n_missing":0,"n_branches":0,"n_partial_branches":0,"n_missing_branches":0}}},"z_d85b5e27f0686b9e_save_py":{"hash":"f4fc059037139e0cf67782fc0746531d","index":{"url":"z_d85b5e27f0686b9e_save_py.html","file":"workflow/tasks/save.py","description":"","nums":{"precision":0,"n_files":1,"n_statements":22,"n_excluded":0,"n_missing":0,"n_branches":0,"n_partial_branches":0,"n_missing_branches":0}}},"z_d85b5e27f0686b9e_transform_py":{"hash":"00bb5b828456df6db8f4d9695362289f","index":{"url":"z_d85b5e27f0686b9e_transform_py.html","file":"workflow/tasks/transform.py","description":"","nums":{"precision":0,"n_files":1,"n_statements":28,"n_excluded":0,"n_missing":0,"n_branches":0,"n_partial_branches":0,"n_missing_branches":0}}},"z_83fb7a5244cf7789_db_py":{"hash":"f6dedc562377f9b0d98b50216d8a8d90","index":{"url":"z_83fb7a5244cf7789_db_py.html","file":"workflow/utils/db.py","description":"","nums":{"precision":0,"n_files":1,"n_statements":25,"n_excluded":0,"n_missing":13,"n_branches":0,"n_partial_branches":0,"n_missing_branches":0}}},"z_83fb7a5244cf7789_math_py":{"hash":"442491175406fc93759992da66f6035d","index":{"url":"z_83fb7a5244cf7789_math_py.html","file":"workflow/utils/math.py","description":"","nums":{"precision":0,"n_files":1,"n_statements":14,"n_excluded":0,"n_missing":0,"n_branches":0,"n_partial_branches":0,"n_missing_branches":0}}},"z_83fb7a5244cf7789_notification_py":{"hash":"923b1c2479ac9ffff882dd6966682ce9","index":{"url":"z_83fb7a5244cf7789_notification_py.html","file":"workflow/utils/notification.py","description":"","nums":{"precision":0,"n_files":1,"n_statements":5,"n_excluded":0,"n_missing":1,"n_branches":0,"n_partial_branches":0,"n_missing_branches":0}}}}}